wordpress/__init__.py
wordpress/admin.py
wordpress/apps.py
wordpress/models.py
wordpress/router.py
wordpress/urls.py
wordpress/views.py
wordpress/templates/wordpress/post_archive.html
wordpress/templates/wordpress/post_archive_author.html
wordpress/templates/wordpress/post_archive_day.html
wordpress/templates/wordpress/post_archive_month.html
wordpress/templates/wordpress/post_archive_year.html
wordpress/templates/wordpress/post_detail.html
wordpress/templates/wordpress/post_term.html
wordpress/templates/wordpress/wxr.xml
the_real_django_wordpress_py3-0.12.1.dist-info/LICENSE
the_real_django_wordpress_py3-0.12.1.dist-info/METADATA
the_real_django_wordpress_py3-0.12.1.dist-info/WHEEL
the_real_django_wordpress_py3-0.12.1.dist-info/top_level.txt
the_real_django_wordpress_py3-0.12.1.dist-info/RECORD
