Metadata-Version: 2.1
Name: the-real-django-wordpress-py3
Version: 0.12.1
Summary: Django models and views for a WordPress database (Django 1.11 or later).
Home-page: http://github.com/2e2a/django-wordpress/
Author: Alexej Starschenko
Author-email: alexej@2e2a.de
License: BSD License
Platform: any
Classifier: Development Status :: 4 - Beta
Classifier: Intended Audience :: Developers
Classifier: License :: OSI Approved :: BSD License
Classifier: Natural Language :: English
Classifier: Operating System :: OS Independent
Classifier: Programming Language :: Python
Classifier: Environment :: Web Environment
License-File: LICENSE
